xenapi/XenAPI.py
xenapi/__init__.py
xenapi/provision.py
xenserver/__init__.py
xenserver/admin.py
xenserver/celery.py
xenserver/forms.py
xenserver/iputil.py
xenserver/models.py
xenserver/settings.py
xenserver/tasks.py
xenserver/testsettings.py
xenserver/urls.py
xenserver/views.py
xenserver/wsgi.py
xenserver/migrations/0001_initial.py
xenserver/migrations/0002_auto_20150109_0905.py
xenserver/migrations/0003_xenserver_active.py
xenserver/migrations/0004_auto_20160622_0825.py
xenserver/migrations/0005_auto_20160624_1107.py
xenserver/migrations/__init__.py
xenserver/static/css/bootstrap-theme.css
xenserver/static/css/bootstrap-theme.css.map
xenserver/static/css/bootstrap-theme.min.css
xenserver/static/css/bootstrap.css
xenserver/static/css/bootstrap.css.map
xenserver/static/css/bootstrap.min.css
xenserver/static/css/dataTables.bootstrap.css
xenserver/static/css/defaults.css
xenserver/static/css/jquery.dataTables.css
xenserver/static/d3/LICENSE
xenserver/static/d3/d3.v3.js
xenserver/static/d3/d3.v3.min.js
xenserver/static/fonts/glyphicons-halflings-regular.eot
xenserver/static/fonts/glyphicons-halflings-regular.svg
xenserver/static/fonts/glyphicons-halflings-regular.ttf
xenserver/static/fonts/glyphicons-halflings-regular.woff
xenserver/static/images/GitHub-Mark-32px.png
xenserver/static/images/back_disabled.png
xenserver/static/images/back_enabled.png
xenserver/static/images/back_enabled_hover.png
xenserver/static/images/favicon.ico
xenserver/static/images/forward_disabled.png
xenserver/static/images/forward_enabled.png
xenserver/static/images/forward_enabled_hover.png
xenserver/static/images/sideloader128.png
xenserver/static/images/sort_asc.png
xenserver/static/images/sort_asc_disabled.png
xenserver/static/images/sort_both.png
xenserver/static/images/sort_desc.png
xenserver/static/images/sort_desc_disabled.png
xenserver/static/images/xenzen32.png
xenserver/static/js/bootstrap.js
xenserver/static/js/bootstrap.min.js
xenzen-1.0.2.dist-info/DESCRIPTION.rst
xenzen-1.0.2.dist-info/LICENSE.txt
xenzen-1.0.2.dist-info/METADATA
xenzen-1.0.2.dist-info/RECORD
xenzen-1.0.2.dist-info/WHEEL
xenzen-1.0.2.dist-info/metadata.json
xenzen-1.0.2.dist-info/top_level.txt
