Metadata-Version: 2.0
Name: xenzen
Version: 1.0.2
Summary: A Django UI for managing XenServer in the simplest possible way.
Home-page: https://github.com/praekeltfoundation/xenzen
Author: Praekelt.org SRE team
Author-email: sre@praekelt.org
License: MIT
Platform: UNKNOWN
Classifier: Development Status :: 5 - Production/Stable
Classifier: Framework :: Django
Classifier: Framework :: Django :: 1.8
Classifier: Intended Audience :: System Administrators
Classifier: License :: OSI Approved :: MIT License
Classifier: Programming Language :: Python :: 2
Classifier: Programming Language :: Python :: 2.7
Requires-Dist: Django (>=1.8,<1.9)
Requires-Dist: celery (>=3.1,<4)
Requires-Dist: django-crispy-forms
Requires-Dist: django-haystack
Requires-Dist: lxml
Requires-Dist: psycopg2
Requires-Dist: pyyaml
Requires-Dist: raven
Requires-Dist: redis
Requires-Dist: social-auth-app-django
